itk_vkfft-0.2.0.dist-info/top_level.txt
itk_vkfft-0.2.0.dist-info/METADATA
itk_vkfft-0.2.0.dist-info/LICENSE
itk_vkfft-0.2.0.dist-info/RECORD
itk_vkfft-0.2.0.dist-info/WHEEL
itk/itkVkComplexToComplex1DFFTImageFilterPython.py
itk/itkVkInverse1DFFTImageFilterPython.py
itk/itkVkComplexToComplexFFTImageFilterPython.py
itk/VkFFTBackendPython.py
itk/itkVkDiscreteGaussianImageFilterPython.py
itk/itkVkForward1DFFTImageFilterPython.py
itk/itkVkMultiResolutionPyramidImageFilterFactoryPython.py
itk/itkVkForwardFFTImageFilterPython.py
itk/itkVkMultiResolutionPyramidImageFilterPython.py
itk/_VkFFTBackendPython.so
itk/itkVkFFTImageFilterInitFactoryPython.py
itk/itkVkRealToHalfHermitianForwardFFTImageFilterPython.py
itk/itkVkGlobalConfigurationPython.py
itk/itkVkHalfHermitianToRealInverseFFTImageFilterPython.py
itk/itkVkInverseFFTImageFilterPython.py
itk/Configuration/VkFFTBackendConfig.py
itk/Configuration/VkFFTBackend_snake_case.py
itk_vkfft.libs/libOpenCL-79939442.so.1
itk_vkfft.libs/libtbb-e251c622.so.12.3
